functions_by_farrukhsadykov/README.md
functions_by_farrukhsadykov/math_functions.py
functions_by_farrukhsadykov-0.3.0.dist-info/WHEEL
functions_by_farrukhsadykov-0.3.0.dist-info/METADATA
functions_by_farrukhsadykov-0.3.0.dist-info/RECORD
